s2l/__init__.py
s2l/main.py
s2l/utils.py
s2l-0.4.1.dist-info/METADATA
s2l-0.4.1.dist-info/WHEEL
s2l-0.4.1.dist-info/entry_points.txt
s2l-0.4.1.dist-info/licenses/LICENSE.txt
s2l-0.4.1.dist-info/RECORD
