Metadata-Version: 2.4
Name: s2l
Version: 0.4.1
Summary: Export your SensCritique data to Letterboxd
Project-URL: Homepage, https://github.com/rx342/senscritique2letterboxd
Project-URL: Issues, https://github.com/rx342/senscritique2letterboxd/issues
Author: rx342
License-File: LICENSE.txt
Requires-Python: >=3.10
Requires-Dist: beautifulsoup4>=4.13.4
Requires-Dist: questionary>=2.1.0
Requires-Dist: requests>=2.32.3
Requires-Dist: rich>=14.0.0
